README.rst
setup.py
./search_replace.py
search_replace.egg-info/PKG-INFO
search_replace.egg-info/SOURCES.txt
search_replace.egg-info/dependency_links.txt
search_replace.egg-info/entry_points.txt
search_replace.egg-info/requires.txt
search_replace.egg-info/top_level.txt