Metadata-Version: 1.1
Name: search-replace
Version: 0.1.2
Summary: A convenience script to search and replace strings in files.
Home-page: https://github.com/luismsgomes/search-replace
Author: Luís Gomes
Author-email: luismsgomes@gmail.com
License: MIT
Keywords: convenience
Platform: UNKNOWN
Classifier: Development Status :: 3 - Alpha
Classifier: License :: OSI Approved :: MIT License
Classifier: Programming Language :: Python :: 3.7
